flask_security_txt.py
flask_securitytxt-1.3.8.dist-info/licenses/LICENCE
flask_securitytxt-1.3.8.dist-info/METADATA
flask_securitytxt-1.3.8.dist-info/WHEEL
flask_securitytxt-1.3.8.dist-info/top_level.txt
flask_securitytxt-1.3.8.dist-info/RECORD
