Metadata-Version: 2.4
Name: Flask-SecurityTxt
Version: 1.3.8
Summary: Flask-SecurityTxt is a Flask extension for creating and serving security.txt files which provide information on reporting security vulnerabilities.
Author-email: "M.P. van de Weerd" <michael@parcifal.dev>
License: LICENCE
Project-URL: Homepage, https://gitlab.com/parcifal/flask-security-txt
Project-URL: Bug Tracker, https://gitlab.com/parcifal/flask-security-txt/-/issues
Keywords: web,security,security.txt
Classifier: Development Status :: 5 - Production/Stable
Classifier: Environment :: Web Environment
Classifier: Framework :: Flask
Classifier: Intended Audience :: Developers
Classifier: License :: OSI Approved :: GNU General Public License v3 (GPLv3)
License-File: LICENCE
Requires-Dist: flask
Requires-Dist: flask-babel
Requires-Dist: pgpy
Requires-Dist: standard-imghdr
Dynamic: license-file
